slacker_game/VT323-Regular.ttf
slacker_game/__init__.py
slacker_game/__main__.py
slacker_game/icon.png
slacker_game-2.1.2.dist-info/entry_points.txt
slacker_game-2.1.2.dist-info/LICENSE
slacker_game-2.1.2.dist-info/WHEEL
slacker_game-2.1.2.dist-info/METADATA
slacker_game-2.1.2.dist-info/RECORD
