Metadata-Version: 2.1
Name: slacker_game
Version: 2.1.2
Summary: A clone of the arcade game Stacker
Home-page: https://sr.ht/~cnx/slacker-game
License: GPLv3+
Keywords: stacker,arcade-game,pygame
Author: Nguyễn Gia Phong
Author-email: mcsinyx@disroot.org
Requires-Python: >=3.7
Classifier: Development Status :: 4 - Beta
Classifier: Environment :: MacOS X
Classifier: Environment :: Win32 (MS Windows)
Classifier: Environment :: X11 Applications
Classifier: Intended Audience :: End Users/Desktop
Classifier: License :: OSI Approved :: GNU General Public License v3 or later (GPLv3+)
Classifier: Natural Language :: English
Classifier: Operating System :: OS Independent
Classifier: Programming Language :: Python :: 3.7
Classifier: Programming Language :: Python :: 3.8
Classifier: Programming Language :: Python :: 3.9
Classifier: Programming Language :: Python :: 3 :: Only
Classifier: Programming Language :: Python
Classifier: Topic :: Games/Entertainment :: Arcade
Requires-Dist: pygame>=2.0.0.dev14
